{
  "version": 2,
  "mode": "linear-sizeMap",
  "sizeUnit": null,
  "sizeStep": 4,
  "suffixToPx": {
    "0": "0",
    "1": "NaNpx",
    "2": "NaNpx",
    "3": "NaNpx",
    "4": "NaNpx",
    "5": "NaNpx",
    "6": "NaNpx",
    "7": "NaNpx",
    "8": "NaNpx",
    "9": "NaNpx",
    "10": "NaNpx",
    "11": "NaNpx",
    "12": "NaNpx",
    "14": "NaNpx",
    "16": "NaNpx",
    "20": "NaNpx",
    "24": "NaNpx",
    "28": "NaNpx",
    "32": "NaNpx",
    "36": "NaNpx",
    "40": "NaNpx",
    "44": "NaNpx",
    "48": "NaNpx",
    "52": "NaNpx",
    "56": "NaNpx",
    "60": "NaNpx",
    "64": "NaNpx",
    "72": "NaNpx",
    "80": "NaNpx",
    "96": "NaNpx",
    "px": "1px",
    "0.5": "NaNpx",
    "1.5": "NaNpx",
    "2.5": "NaNpx",
    "3.5": "NaNpx"
  },
  "stepLabels": [
    {
      "suffix": "0",
      "zh": "No spacing",
      "en": "None (0)"
    },
    {
      "suffix": "px",
      "zh": "1px hairline",
      "en": "1px hairline"
    },
    {
      "suffix": "0.5",
      "zh": "Half-step · NaNpx",
      "en": "Half-step · NaNpx"
    },
    {
      "suffix": "1",
      "zh": "Extra-tight · NaNpx",
      "en": "XS · NaNpx"
    },
    {
      "suffix": "1.5",
      "zh": "Compact · NaNpx",
      "en": "SM · NaNpx"
    },
    {
      "suffix": "2",
      "zh": "Compact · NaNpx",
      "en": "SM · NaNpx"
    },
    {
      "suffix": "2.5",
      "zh": "Dense · NaNpx",
      "en": "MD · NaNpx"
    },
    {
      "suffix": "3",
      "zh": "Dense · NaNpx",
      "en": "MD · NaNpx"
    },
    {
      "suffix": "3.5",
      "zh": "Small · NaNpx",
      "en": "LG · NaNpx"
    },
    {
      "suffix": "4",
      "zh": "Small · NaNpx",
      "en": "LG · NaNpx"
    },
    {
      "suffix": "5",
      "zh": "Balanced · NaNpx",
      "en": "XL · NaNpx"
    },
    {
      "suffix": "6",
      "zh": "Comfortable · NaNpx",
      "en": "2XL · NaNpx"
    },
    {
      "suffix": "7",
      "zh": "Relaxed · NaNpx",
      "en": "3XL · NaNpx"
    },
    {
      "suffix": "8",
      "zh": "Large · NaNpx",
      "en": "4XL · NaNpx"
    },
    {
      "suffix": "9",
      "zh": "Section · NaNpx",
      "en": "5XL · NaNpx"
    },
    {
      "suffix": "10",
      "zh": "Large section · NaNpx",
      "en": "6XL · NaNpx"
    },
    {
      "suffix": "11",
      "zh": "Extra-large · NaNpx",
      "en": "7XL · NaNpx"
    },
    {
      "suffix": "12",
      "zh": "Huge · NaNpx",
      "en": "8XL · NaNpx"
    },
    {
      "suffix": "14",
      "zh": "Full-width · NaNpx",
      "en": "10XL · NaNpx"
    },
    {
      "suffix": "16",
      "zh": "Maximum · NaNpx",
      "en": "12XL · NaNpx"
    },
    {
      "suffix": "20",
      "zh": "Step 20 · NaNpx",
      "en": "Step 20 · NaNpx"
    },
    {
      "suffix": "24",
      "zh": "Step 24 · NaNpx",
      "en": "Step 24 · NaNpx"
    },
    {
      "suffix": "28",
      "zh": "Step 28 · NaNpx",
      "en": "Step 28 · NaNpx"
    },
    {
      "suffix": "32",
      "zh": "Step 32 · NaNpx",
      "en": "Step 32 · NaNpx"
    },
    {
      "suffix": "36",
      "zh": "Step 36 · NaNpx",
      "en": "Step 36 · NaNpx"
    },
    {
      "suffix": "40",
      "zh": "Step 40 · NaNpx",
      "en": "Step 40 · NaNpx"
    },
    {
      "suffix": "44",
      "zh": "Step 44 · NaNpx",
      "en": "Step 44 · NaNpx"
    },
    {
      "suffix": "48",
      "zh": "Step 48 · NaNpx",
      "en": "Step 48 · NaNpx"
    },
    {
      "suffix": "52",
      "zh": "Step 52 · NaNpx",
      "en": "Step 52 · NaNpx"
    },
    {
      "suffix": "56",
      "zh": "Step 56 · NaNpx",
      "en": "Step 56 · NaNpx"
    },
    {
      "suffix": "60",
      "zh": "Step 60 · NaNpx",
      "en": "Step 60 · NaNpx"
    },
    {
      "suffix": "64",
      "zh": "Step 64 · NaNpx",
      "en": "Step 64 · NaNpx"
    },
    {
      "suffix": "72",
      "zh": "Step 72 · NaNpx",
      "en": "Step 72 · NaNpx"
    },
    {
      "suffix": "80",
      "zh": "Step 80 · NaNpx",
      "en": "Step 80 · NaNpx"
    },
    {
      "suffix": "96",
      "zh": "Step 96 · NaNpx",
      "en": "Step 96 · NaNpx"
    }
  ]
}
